gerapy_pyppeteer/__init__.py
gerapy_pyppeteer/__version__.py
gerapy_pyppeteer/downloadermiddlewares.py
gerapy_pyppeteer/pretend.py
gerapy_pyppeteer/request.py
gerapy_pyppeteer/settings.py
gerapy_pyppeteer-0.2.4.dist-info/METADATA
gerapy_pyppeteer-0.2.4.dist-info/WHEEL
gerapy_pyppeteer-0.2.4.dist-info/top_level.txt
gerapy_pyppeteer-0.2.4.dist-info/RECORD
