Metadata-Version: 2.1
Name: gerapy-pyppeteer
Version: 0.2.4
Summary: Pyppeteer Components for Scrapy & Gerapy
Home-page: https://github.com/Gerapy/GerapyPyppeteer
Author: Germey
Author-email: cqc@cuiqingcai.com
License: MIT
Platform: UNKNOWN
Classifier: License :: OSI Approved :: MIT License
Classifier: Programming Language :: Python :: 3.6
Classifier: Programming Language :: Python :: 3.7
Classifier: Programming Language :: Python :: 3.8
Classifier: Programming Language :: Python :: Implementation :: CPython
Classifier: Programming Language :: Python :: Implementation :: PyPy
Requires-Python: >=3.6.0
